[
  {
    "chain_code": "tbtc",
    "name": "Bitcoin TestNet3",
    "fee_code": "tbtc",
    "chain_model": "utxo",
    "curve": "secp256k1",
    "bip44_coin_type": 1,
    "bip44_auto_increment_level": "ACCOUNT",
    "default_address_encoding": "P2WPKH-P2SH",
    "bip44_purpose_options": {
      "P2PKH": 44,
      "P2WPKH-P2SH": 49,
      "P2WPKH": 84
    },
    "coins": [
      {
        "code": "tbtc",
        "symbol": "TBTC",
        "name": "Bitcoin TestNet3",
        "decimals": 8,
        "icon": "https://onekey.243096.com/onekey/images/token/btc/BTC.png"
      }
    ],
    "chain_affinity": "btc",
    "qr_code_prefix": "bitcoin"
  },
  {
    "chain_code": "teth",
    "name": "Ethereum Ropsten Test Network",
    "fee_code": "teth",
    "chain_model": "account",
    "curve": "secp256k1",
    "bip44_coin_type": 60,
    "fee_price_decimals_for_legibility": 9,
    "coins": [
      {
        "code": "teth",
        "symbol": "TETH",
        "name": "Ethereum Ropsten Test Network",
        "decimals": 18,
        "icon": "https://onekey.243096.com/onekey/images/token/eth/ETH.png"
      }
    ],
    "clients": [
      {
        "class": "Geth",
        "url": "https://ropsten.infura.io/v3/f001ce716b6e4a33a557f74df6fe8eff"
      },
      {
        "class": "BlockBook",
        "url": "https://ropsten1.trezor.io"
      },
      {
        "class": "Etherscan",
        "url": "https://api-ropsten.etherscan.io",
        "api_keys": [
          "R796P9T31MEA24P8FNDZBCA88UHW8YCNVW"
        ]
      }
    ],
    "chain_affinity": "eth",
    "qr_code_prefix": "ethereum",
    "chain_id": "3"
  },
  {
    "chain_code": "tbsc",
    "name": "Binance Smart Chain Test Network",
    "fee_code": "tbsc",
    "chain_model": "account",
    "curve": "secp256k1",
    "bip44_coin_type": 60,
    "fee_price_decimals_for_legibility": 9,
    "coins": [
      {
        "code": "tbsc",
        "symbol": "TBNB",
        "name": "Binance Smart Chain Test Network",
        "decimals": 18,
        "icon": "https://onekey.243096.com/onekey/images/token/bsc/BSC.png"
      }
    ],
    "clients": [
      {
        "class": "Geth",
        "url": "https://data-seed-prebsc-2-s1.binance.org:8545"
      }
    ],
    "chain_affinity": "eth",
    "qr_code_prefix": "bsc",
    "chain_id": "97"
  },
  {
    "chain_code": "theco",
    "name": "Fork Huobi ECO Chain",
    "fee_code": "theco",
    "chain_model": "account",
    "curve": "secp256k1",
    "bip44_coin_type": 60,
    "fee_price_decimals_for_legibility": 9,
    "coins": [
      {
        "code": "theco",
        "symbol": "THT",
        "name": "Huobi ECO Chain Test Network",
        "decimals": 18,
        "icon": "https://onekey.243096.com/onekey/images/token/heco/HECO.png"
      }
    ],
    "clients": [
      {
        "class": "Geth",
        "url": "https://testnode.onekey.so/heco"
      }
    ],
    "chain_affinity": "eth",
    "qr_code_prefix": "heco",
    "chain_id": "128"
  },
  {
    "chain_code": "tokt",
    "name": "OKExChain Testnet",
    "fee_code": "tokt",
    "chain_model": "account",
    "curve": "secp256k1",
    "bip44_coin_type": 60,
    "fee_price_decimals_for_legibility": 9,
    "coins": [
      {
        "code": "tokt",
        "symbol": "TOKT",
        "name": "OKExChain Testnet",
        "decimals": 18,
        "icon": "https://onekey.243096.com/onekey/images/token/okt/OKT.png"
      }
    ],
    "clients": [
      {
        "class": "Geth",
        "url": "https://exchaintestrpc.okex.org"
      }
    ],
    "chain_affinity": "eth",
    "qr_code_prefix": "okt",
    "chain_id": "65"
  }
]
